sklearn_lvq/__init__.py
sklearn_lvq/glvq.py
sklearn_lvq/gmlvq.py
sklearn_lvq/grlvq.py
sklearn_lvq/grmlvq.py
sklearn_lvq/lgmlvq.py
sklearn_lvq/lmrslvq.py
sklearn_lvq/lvq.py
sklearn_lvq/mrslvq.py
sklearn_lvq/rslvq.py
sklearn_lvq/utils.py
sklearn_lvq/tests/__init__.py
sklearn_lvq/tests/ignored_test_docstring_parameters.py
sklearn_lvq/tests/test_glvq.py
sklearn_lvq/tests/test_rslvq.py
sklearn_lvq-1.1.1.dist-info/LICENSE
sklearn_lvq-1.1.1.dist-info/METADATA
sklearn_lvq-1.1.1.dist-info/WHEEL
sklearn_lvq-1.1.1.dist-info/top_level.txt
sklearn_lvq-1.1.1.dist-info/RECORD
