Metadata-Version: 2.1
Name: sklearn-lvq
Version: 1.1.1
Summary: Scikit-Learn compatible Generalized Learning Vector Quantization (GLVQ) and Robust Soft Learning Vector Quantization implementation.
Home-page: https://github.com/MrNuggelz/sklearn-lvq
Author: Joris Jensun
Author-email: jjensen@techfak.uni-bielefeld.de
License: BSD-3-Clause
Download-URL: https://github.com/MrNuggelz/sklearn-lvq/releases/tag/1.1.0
Platform: UNKNOWN
Classifier: Intended Audience :: Developers
Classifier: Intended Audience :: Education
Classifier: Intended Audience :: Science/Research
Classifier: License :: OSI Approved :: BSD License
Classifier: Programming Language :: Python :: 2.7
Classifier: Programming Language :: Python :: 3.5
Classifier: Programming Language :: Python :: 3.6
Classifier: Programming Language :: Python :: 3.7
Classifier: Programming Language :: Python :: 3.8
Classifier: Operating System :: OS Independent
Classifier: Topic :: Scientific/Engineering :: Artificial Intelligence
Classifier: Topic :: Software Development :: Libraries
Classifier: Topic :: Software Development :: Libraries :: Python Modules
Provides-Extra: examples
Provides-Extra: tests
Provides-Extra: docs
